drone_env/__init__.py
drone_env/envs/__init__.py
drone_env/envs/drone_env.py
drone_env/envs/simulink_connect.py
drone_env/envs/track_generation.py
drone_env/envs/utils.py
drone_env/wrappers/__init__.py
drone_env-0.0.3.dist-info/METADATA
drone_env-0.0.3.dist-info/WHEEL
drone_env-0.0.3.dist-info/top_level.txt
drone_env-0.0.3.dist-info/RECORD
